Icons/BackgroundIcon.png
Icons/ExitIcon.png
Icons/LogIcon.png
Icons/MCIcon.png
Icons/MCMCIcon.png
Icons/Mirror.png
Icons/PeakIcon.png
Icons/RefreshIcon.png
Icons/RegionSelectionIcon.png
Icons/SumIcon.png
Icons/TestIcon.png
Icons/YScaleIcon.png
Icons/ZoomIcon.png
Icons/ZoomInIcon.png
Icons/ZoomOutIcon.png
Icons/__init__.py
Icons/gaussFitIcon.png
Icons/probIcon.png
Spec/Data_Handler - Copy.py
Spec/Data_Handler.py
Spec/Modules - Copy.py
Spec/Modules.py
Spec/Spec.py
Spec/Spectrum_GUI.py
Spec/__init__.py
Spec/default_data - Copy.txt
Spec/test_data_storage - Copy.dat
Spec/testing - Copy.dat
Spec/used_file_storage - Copy.txt
Spec/Icons/BackgroundIcon.png
Spec/Icons/ExitIcon.png
Spec/Icons/LogIcon.png
Spec/Icons/MCIcon.png
Spec/Icons/MCMCIcon.png
Spec/Icons/Mirror.png
Spec/Icons/PeakIcon.png
Spec/Icons/RefreshIcon.png
Spec/Icons/RegionSelectionIcon.png
Spec/Icons/SumIcon.png
Spec/Icons/TestIcon.png
Spec/Icons/YScaleIcon.png
Spec/Icons/ZoomIcon.png
Spec/Icons/ZoomInIcon.png
Spec/Icons/ZoomOutIcon.png
Spec/Icons/__init__.py
Spec/Icons/gaussFitIcon.png
Spec/Icons/probIcon.png
SpecAnalysis_cader_Cademan051-1.5.5.dist-info/LICENSE.txt
SpecAnalysis_cader_Cademan051-1.5.5.dist-info/METADATA
SpecAnalysis_cader_Cademan051-1.5.5.dist-info/WHEEL
SpecAnalysis_cader_Cademan051-1.5.5.dist-info/top_level.txt
SpecAnalysis_cader_Cademan051-1.5.5.dist-info/RECORD
